__init__.py
toml_package/__init__.py
toml_package/tomlpack.py
toml_package-0.0.2.dist-info/LICENSE
toml_package-0.0.2.dist-info/METADATA
toml_package-0.0.2.dist-info/WHEEL
toml_package-0.0.2.dist-info/top_level.txt
toml_package-0.0.2.dist-info/RECORD
