Metadata-Version: 2.1
Name: toml-package
Version: 0.0.2
Summary: Packing using pyproject.tom and setuptools
Author-email: Mohammad Mahfooz Alam <mahfooz.iiitian@gmail.com>
Project-URL: Homepage, https://github.com/pypa/PackageToProject
Project-URL: Bug Tracker, https://github.com/pypa/PackageToProject/issues
Classifier: Programming Language :: Python :: 3
Classifier: License :: OSI Approved :: MIT License
Classifier: Operating System :: OS Independent
Requires-Python: >=3.8
License-File: LICENSE
